AUTHORS.rst
CHANGELOG.rst
LICENSE
MANIFEST.in
README.rst
setup.py
dfp/__init__.py
dfp/models.py
dfp/templates/basic/dfp/dfp_footer.html
dfp/templatetags/__init__.py
dfp/templatetags/__init__.pyc
dfp/templatetags/dfp_tags.py
dfp/templatetags/dfp_tags.pyc
django_dfp.egg-info/PKG-INFO
django_dfp.egg-info/SOURCES.txt
django_dfp.egg-info/dependency_links.txt
django_dfp.egg-info/not-zip-safe
django_dfp.egg-info/requires.txt
django_dfp.egg-info/top_level.txt